nxslib/__init__.py
nxslib/comm.py
nxslib/dev.py
nxslib/logger.py
nxslib/nxscope.py
nxslib/py.typed
nxslib/thread.py
nxslib/intf/dummy.py
nxslib/intf/iintf.py
nxslib/intf/rtt.py
nxslib/intf/serial.py
nxslib/proto/iframe.py
nxslib/proto/iparse.py
nxslib/proto/iparserecv.py
nxslib/proto/parse.py
nxslib/proto/parserecv.py
nxslib/proto/serialframe.py
nxslib-0.9.1.dist-info/LICENSE
nxslib-0.9.1.dist-info/METADATA
nxslib-0.9.1.dist-info/WHEEL
nxslib-0.9.1.dist-info/top_level.txt
nxslib-0.9.1.dist-info/RECORD
