Metadata-Version: 2.1
Name: nxslib
Version: 0.9.1
Summary: NxScope client library
Author-email: raiden00 <raiden00@railab.me>
License: Apache-2.0
Project-URL: Changelog, https://github.com/railab/nxslib/blob/master/CHANGES.md
Project-URL: Homepage, https://github.com/railab/nxslib
Keywords: nuttx
Classifier: Development Status :: 4 - Beta
Classifier: Intended Audience :: Developers
Classifier: License :: OSI Approved :: Apache Software License
Classifier: Programming Language :: Python :: 3.10
Classifier: Programming Language :: Python :: 3.11
Classifier: Topic :: Software Development :: Embedded Systems
Classifier: Operating System :: OS Independent
Requires-Python: >=3.10
License-File: LICENSE
Requires-Dist: pyserial >=3.5
Requires-Dist: crcmod >=1.7
Requires-Dist: pylink-square >=1.2
